cowsuper/BaseClassifier.py
cowsuper/CLL.py
cowsuper/ConstraintEstimator.py
cowsuper/DCWS.py
cowsuper/__init__.py
cowsuper/log.py
cowsuper/utilities.py
cowsuper/examples/run_experiments.py
cowsuper/examples/datasets/generate_weak_signals.ipynb
cowsuper/examples/datasets/generate_weak_signals.py
cowsuper/examples/datasets/breast-cancer/data_features.npy
cowsuper/examples/datasets/breast-cancer/data_labels.npy
cowsuper/examples/datasets/breast-cancer/test_features.npy
cowsuper/examples/datasets/breast-cancer/test_labels.npy
cowsuper/examples/datasets/breast-cancer/wdbc.data
cowsuper/examples/datasets/breast-cancer/weak_signals.npy
cowsuper/examples/datasets/sst-2/data_features.npy
cowsuper/examples/datasets/sst-2/data_labels.npy
cowsuper/examples/datasets/sst-2/sst2-test.csv
cowsuper/examples/datasets/sst-2/sst2-train.csv
cowsuper/examples/datasets/sst-2/test_features.npy
cowsuper/examples/datasets/sst-2/test_labels.npy
cowsuper/examples/datasets/sst-2/weak_signals.npy
cowsuper/examples/datasets/svhn/test_32x32.mat
cowsuper-0.0.2.dist-info/METADATA
cowsuper-0.0.2.dist-info/WHEEL
cowsuper-0.0.2.dist-info/licenses/LICENSE
cowsuper-0.0.2.dist-info/RECORD
