Metadata-Version: 2.1
Name: CoWSuper
Version: 0.0.2
Summary: A tool that produces labels using weakly supervised learning with constraint-based methods.
Project-URL: Homepage, https://github.com/jianhui-chen/CoWSuper
Author-email: Bert Huang <bert@cs.tufts.edu>
License: MIT License
Classifier: License :: OSI Approved :: MIT License
Classifier: Operating System :: OS Independent
Classifier: Programming Language :: Python :: 3
Requires-Python: >=3.6
